dimc/__init__.py
dimc/dimc.py
dimc-0.2.2.dist-info/LICENSE
dimc-0.2.2.dist-info/METADATA
dimc-0.2.2.dist-info/WHEEL
dimc-0.2.2.dist-info/top_level.txt
dimc-0.2.2.dist-info/RECORD
